[
        {
            "name":"wordpress2",
            "hostname": "wordpress2",
            "image": "wordpress:latest",
            "url": "wp2.wordpress.0rn.de",
            "volumes": "{{ docker_dir }}/wordpress2:/var/www/html"
        },
        {
            "name":"wordpress3",
            "hostname": "wordpress3",
            "image": "wordpress:5.0.1",
            "url": "wp3.wordpress.0rn.de",
            "volumes": "{{ docker_dir }}/wordpress3:/var/www/html"
        },
        {
            "name":"wordpress4",
            "hostname": "wordpress4",
            "image": "wordpress:4.7",
            "url": "presspot.duckdns.org",
            "volumes": "{{ docker_dir }}/wordpress4:/var/www/html"
        },
        {
            "name":"wordpress5",
            "hostname": "wordpress5",
            "image": "wordpress:5.0.1",
            "url": "bl1.blog.0rn.de",
            "volumes": "{{ docker_dir }}/wordpress5:/var/www/html"
        },
        {
            "name":"wordpress6",
            "hostname": "wordpress6",
            "image": "wordpress:4.7",
            "url": "shop.blog.0rn.de",
            "volumes": "{{ docker_dir }}/wordpress6:/var/www/html"
        },
        {
            "name":"wordpress7",
            "hostname": "wordpress7",
            "image": "wordpress:latest",
            "url": "shopypot.duckdns.org",
            "volumes": "{{ docker_dir }}/wordpress7:/var/www/html"
        }
]
